{
	"bmi-installation" : null,
	"compiler-frontend-variant" : "MSVC",
	"compiler-id" : "MSVC",
	"compiler-simulate-id" : "",
	"config" : "Debug",
	"cxx-modules" : {},
	"dir-cur-bld" : "D:/Dev/Vulkan/VuMake/cmake-build-debug",
	"dir-cur-src" : "D:/Dev/Vulkan/VuMake",
	"dir-top-bld" : "D:/Dev/Vulkan/VuMake/cmake-build-debug",
	"dir-top-src" : "D:/Dev/Vulkan/VuMake",
	"exports" : [],
	"forward-modules-from-target-dirs" : [],
	"include-dirs" : 
	[
		"D:\\Dev\\Vulkan\\VuMake\\src\\common",
		"D:\\Dev\\Vulkan\\VuMake\\src\\components",
		"D:\\Dev\\Vulkan\\VuMake\\src\\systems",
		"D:\\Dev\\Vulkan\\VuMake\\src\\render",
		"D:\\Dev\\Vulkan\\VuMake\\src\\material",
		"D:\\Dev\\Vulkan\\VuMake\\src\\math",
		"D:\\Dev\\Vulkan\\VuMake\\src\\util",
		"D:\\Dev\\Vulkan\\VuMake\\external\\imgui",
		"D:\\Dev\\Vulkan\\VuMake\\external\\stb",
		"C:\\VulkanSDK\\1.4.304.1\\Include",
		"D:\\Dev\\Vulkan\\VuMake\\GPUOpen::VulkanMemoryAllocator",
		"_deps\\fetch_buddy_alloc-src",
		"_deps\\fetch_volk-src",
		"_deps\\fetch_vma-src\\include",
		"_deps\\fetch_sdl-build\\include-revision",
		"_deps\\fetch_sdl-src\\include",
		"_deps\\fetch_fastgltf-src\\include",
		"_deps\\fetch_fastgltf-src\\deps\\simdjson",
		"_deps\\fetch_flecs-src\\include",
		"_deps\\fetch_tracy-src\\public"
	],
	"language" : "CXX",
	"linked-target-dirs" : [],
	"module-dir" : "D:/Dev/Vulkan/VuMake/cmake-build-debug/CMakeFiles/VuMake.dir"
}